COPYING
README.rst
pyproject.toml
setup.cfg
sq1090_console.egg-info/PKG-INFO
sq1090_console.egg-info/SOURCES.txt
sq1090_console.egg-info/dependency_links.txt
sq1090_console.egg-info/requires.txt
sq1090_console.egg-info/top_level.txt
sq1090console/__init__.py
sq1090console/console.py
sq1090console/py.typed
sq1090console/web/bootstrap.css
sq1090console/web/bootstrap.css.map
sq1090console/web/bootstrap.js
sq1090console/web/console.css
sq1090console/web/console.js
sq1090console/web/index.html
sq1090console/web/jquery.js
sq1090console/web/maplibre-gl.css
sq1090console/web/maplibre-gl.js
sq1090console/web/plane-16x16.png
sq1090console/web/timeline.css
sq1090console/web/timeline.js